{
  "channels": {
    "DE": {
      "123.tv" : "",
      "13th Street Universal" : "",
      "3+" : "",
      "3sat" : "",
      "A&amp;E" : "",
      "Adult Channel" : "",
      "Al Jazeera" : "",
      "Animal Planet" : "",
      "ANIXE" : "",
      "ARD alpha" : "",
      "ARTE" : "",
      "ATV" : "",
      "ATV II" : "",
      "Auto Motor Sport" : "",
      "AXN" : "",
      "BBC Entertainment" : "",
      "BBC World News" : "",
      "Beate-Uhse.TV" : "",
      "Belgien 1" : "",
      "Bibel TV" : "",
      "Bloomberg Europe TV" : "",
      "Blue Movie" : "",
      "Blue Movie 2" : "",
      "Blue Movie 3" : "",
      "Bon Gusto" : "",
      "Boomerang" : "",
      "BR Nord" : "",
      "BR Süd" : "",
      "Cartoon Network" : "",
      "Channel21" : "",
      "Classica" : "",
      "CNBC" : "",
      "CNN International" : "",
      "Comedy Central" : "",
      "Das Erste" : "ard.de",
      "DAZN" : "",
      "DELUXE MUSIC" : "",
      "Der Aktionär TV" : "",
      "Deutsches Musik Fernsehen" : "",
      "Discovery HD" : "",
      "Disney Channel" : "",
      "Disney Cinemagic (HD)" : "",
      "Disney Junior" : "",
      "Disney XD" : "",
      "DMAX" : "",
      "DR1" : "",
      "DW (Europe)" : "",
      "E! Entertainment" : "",
      "eoTV" : "",
      "eSports1" : "",
      "euronews (en)" : "",
      "euronews (ger)" : "",
      "Eurosport 1" : "",
      "Eurosport 2" : "",
      "EXTREME SPORTS" : "",
      "Fashion TV" : "",
      "Fine Living Network" : "",
      "Fix &amp; Foxi" : "",
      "Food Network" : "",
      "FOX" : "",
      "France 24 (engl.)" : "",
      "France 24 (franz.)" : "",
      "freenet SHOPPING" : "",
      "GEO Television" : "",
      "Goldstar TV" : "",
      "Gute Laune TV" : "",
      "Hamburg 1" : "",
      "Health TV" : "",
      "Heimatkanal" : "",
      "History HD" : "",
      "HR" : "",
      "HSE24" : "",
      "Jukebox" : "",
      "Junior" : "",
      "kabel eins" : "",
      "kabel eins classics" : "",
      "kabel eins Doku" : "",
      "KiKA" : "",
      "KinoweltTV" : "",
      "Köln.tv" : "",
      "K-TV" : "",
      "Leipzig Fernsehen" : "",
      "LUST PUR" : "",
      "Marco Polo TV" : "",
      "MDR Sachsen" : "",
      "MDR Sachsen-Anhalt" : "",
      "MDR Thüringen" : "",
      "Melodie TV" : "",
      "Mezzo" : "",
      "münchen2" : "",
      "münchen.tv" : "",
      "Motors TV" : "",
      "Motorvision TV" : "",
      "MTV" : "",
      "MTV Base" : "",
      "MTV Dance" : "",
      "MTV Hits" : "",
      "MTV Live HD" : "",
      "N24 Doku" : "",
      "Nat Geo HD" : "",
      "NAT GEO WILD" : "",
      "Nautical Channel" : "",
      "NDR HH" : "",
      "NDR MV" : "",
      "NDR NI" : "",
      "NDR SH" : "",
      "NHK World TV" : "",
      "nick" : "",
      "Nick Jr." : "",
      "Nicktoons" : "",
      "NITRO" : "",
      "NOW US" : "",
      "NPO 1" : "",
      "NPO 2" : "",
      "NPO 3" : "",
      "n-tv" : "",
      "oe24.TV" : "",
      "ONE" : "",
      "ORF 1" : "",
      "ORF 2" : "",
      "ORF III" : "",
      "ORF SPORT +" : "",
      "PHOENIX" : "",
      "Planet" : "",
      "Playboy TV" : "",
      "ProSieben" : "",
      "ProSieben Fun" : "",
      "ProSieben MAXX" : "",
      "PULS 4" : "",
      "PULS acht" : "",
      "QVC" : "",
      "QVC2" : "",
      "QVC Style " : "",
      "Radio Bremen TV" : "",
      "RBB Berlin" : "",
      "RBB Brandenburg" : "",
      "RCK TV" : "",
      "Regio TV" : "",
      "Regio TV Bodensee" : "",
      "rheinmaintv" : "",
      "Rhein-Neckar Fernsehen" : "",
      "RiC" : "",
      "Romance TV" : "",
      "RTL" : "",
      "RTL Crime" : "",
      "RTL II" : "",
      "RTL Living" : "",
      "RTL Passion" : "",
      "RTLplus" : "",
      "Sachsen Fernsehen" : "",
      "SAT.1" : "",
      "SAT.1 emotions" : "",
      "SAT.1 Gold" : "",
      "ServusTV" : "",
      "Silverline" : "",
      "sixx" : "",
      "Sky 1" : "",
      "Sky Action" : "",
      "Sky Arts HD" : "",
      "Sky Atlantic HD" : "",
      "Sky Cinema" : "",
      "Sky Cinema+1" : "",
      "Sky Cinema+24" : "",
      "Sky Comedy" : "",
      "Sky Emotion" : "",
      "Sky Family" : "",
      "Sky Hits HD" : "",
      "Sky Krimi" : "",
      "Sky Nostalgie" : "",
      "Sky select" : "",
      "Sky Sport Austria" : "",
      "Sky Sport Bundesliga" : "",
      "Sky Sport HD 1" : "",
      "Sky Sport HD 2" : "",
      "Sky Sport News HD" : "",
      "SKY Sport UHD" : "",
      "Sonnenklar.TV" : "",
      "Sony Entertainment Television" : "",
      "Spiegel Geschichte" : "",
      "Spiegel TV Wissen" : "",
      "SPORT1" : "",
      "SPORT1+" : "",
      "sportdigital" : "",
      "SR" : "",
      "SRF 1" : "",
      "SRF zwei" : "",
      "STAR TV" : "",
      "SUPER RTL" : "",
      "SWR BW" : "",
      "SWR RP" : "",
      "Syfy" : "",
      "tagesschau24" : "",
      "Tele 5" : "",
      "TLC" : "",
      "TNT Comedy" : "",
      "TNT Film" : "",
      "TNT Serie" : "",
      "TOGGO plus" : "",
      "Trace TV" : "",
      "Travel Channel" : "",
      "travelxp 4K" : "",
      "TV2" : "",
      "TV5 Monde" : "",
      "tv.berlin" : "",
      "Universal Channel HD" : "",
      "VH1 Classic" : "",
      "VOX" : "",
      "WDR Aachen" : "",
      "WDR Bielefeld" : "",
      "WDR Bonn" : "",
      "WDR Dortmund" : "",
      "WDR Düsseldorf" : "",
      "WDR Duisburg" : "",
      "WDR Essen" : "",
      "WDR Köln" : "",
      "WDR Münster" : "",
      "WDR Siegen" : "",
      "WDR Wuppertal" : "",
      "WELT" : "",
      "Welt der Wunder TV" : "",
      "Wetter.com TV" : "",
      "ZDF" : "",
      "ZDFinfo" : "",
      "ZDFneo" : "",
      "Zee.One" : "Zee.One"
          }
  }
}